yahpo_gym/__init__.py
yahpo_gym/about.py
yahpo_gym/benchmark_set.py
yahpo_gym/configuration.py
yahpo_gym/get_suite.py
yahpo_gym/local_config.py
yahpo_gym/benchmarks/__init__.py
yahpo_gym/benchmarks/download_checks.py
yahpo_gym/benchmarks/fcnet.py
yahpo_gym/benchmarks/iaml.py
yahpo_gym/benchmarks/lcbench.py
yahpo_gym/benchmarks/nb301.py
yahpo_gym/benchmarks/rbv2.py
yahpo_gym/benchmarks/taskset.py
yahpo_gym-1.0.2.dist-info/LICENSE
yahpo_gym-1.0.2.dist-info/METADATA
yahpo_gym-1.0.2.dist-info/WHEEL
yahpo_gym-1.0.2.dist-info/top_level.txt
yahpo_gym-1.0.2.dist-info/RECORD
