Metadata-Version: 2.1
Name: yahpo_gym
Version: 1.0.2
Summary: Inference module for YAHPO Gym
Home-page: https://github.com/slds-lmu/yahpo_gym
Author: Florian Pfisterer, Lennart Schneider
License: Apache-2.0
Keywords: module,train,yahpo
Classifier: Development Status :: 3 - Alpha
License-File: LICENSE
Requires-Dist: onnxruntime >=1.10.0
Requires-Dist: pyyaml
Requires-Dist: configspace <=0.6.1
Requires-Dist: numpy <2.0.0
Requires-Dist: pandas
Provides-Extra: docs
Requires-Dist: sphinx ; extra == 'docs'
Requires-Dist: sphinx-gallery ; extra == 'docs'
Requires-Dist: sphinx-bootstrap-theme ; extra == 'docs'
Requires-Dist: numpydoc ; extra == 'docs'
Requires-Dist: pandas ; extra == 'docs'
Provides-Extra: test
Requires-Dist: pytest >=4.6 ; extra == 'test'
Requires-Dist: mypy ; extra == 'test'
Requires-Dist: pre-commit ; extra == 'test'
Requires-Dist: pytest-cov ; extra == 'test'
